snektris/__init__.py
snektris/blocks.py
snektris/network.py
snektris/snektris.py
snektris-0.0.3.dist-info/entry_points.txt
snektris-0.0.3.dist-info/LICENSE
snektris-0.0.3.dist-info/WHEEL
snektris-0.0.3.dist-info/METADATA
snektris-0.0.3.dist-info/RECORD
