Metadata-Version: 2.1
Name: snektris
Version: 0.0.3
Summary: SNEKTRIS
Home-page: https://github.com/gab50000/snektris
Author: Gabriel Kabbe
Author-email: gabriel.kabbe@mail.de
Classifier: License :: OSI Approved :: GNU General Public License v3 or later (GPLv3+)
Requires-Dist: pygame
